djasa/__init__.py
djasa/admin.py
djasa/apps.py
djasa/urls.py
djasa/views.py
djasa/conf/__init__.py
djasa/conf/settings.py
djasa/migrations/0001_initial.py
djasa/migrations/__init__.py
djasa/models/__init__.py
djasa/models/abstract.py
djasa/models/chat.py
djasa/models/manager.py
djasa/templates/change_form.html
djasa/templates/change_list.html
djasa/templates/chat_interface.html
djasa/utils/__init__.py
djasa/utils/exceptions.py
djasa/utils/rasa_helpers.py
djasa-0.0.1.dist-info/METADATA
djasa-0.0.1.dist-info/WHEEL
djasa-0.0.1.dist-info/licenses/LICENSE
djasa-0.0.1.dist-info/RECORD
