Metadata-Version: 2.1
Name: djasa
Version: 0.0.1
Summary: A Django package designed to seamlessly integrate Rasa into Django projects. Modular, maintainable, and user-friendly.
Project-URL: Homepage, https://github.com/godd0t/djasa
Author-email: godd0t <lirrishala@gmail.com>
License: MIT
License-File: LICENSE
Requires-Python: >=3.11
Requires-Dist: django>=4.2.5
Requires-Dist: rasa-sdk>=1.4.0
Requires-Dist: requests>=2.31.0
Requires-Dist: ruamel-yaml>=0.17.32
